examples/__init__.py
examples/aiohttp/README.rst
examples/aiohttp/__init__.py
examples/aiohttp/main.py
examples/aiohttp/models.py
examples/basic.py
examples/basic_comments.py
examples/blacksheep/README.md
examples/blacksheep/__init__.py
examples/blacksheep/_tests.py
examples/blacksheep/models.py
examples/blacksheep/server.py
examples/complex_filtering.py
examples/complex_prefetching.py
examples/enum_fields.py
examples/fastapi/.gitignore
examples/fastapi/README.rst
examples/fastapi/__init__.py
examples/fastapi/_tests.py
examples/fastapi/config.py
examples/fastapi/main.py
examples/fastapi/main_custom_timezone.py
examples/fastapi/models.py
examples/fastapi/routers.py
examples/fastapi/schemas.py
examples/functions.py
examples/global_table_name_generator.py
examples/group_by.py
examples/manual_sql.py
examples/postgres.py
examples/pydantic/__init__.py
examples/pydantic/basic.py
examples/pydantic/early_init.py
examples/pydantic/recursive.py
examples/pydantic/tutorial_1.py
examples/pydantic/tutorial_2.py
examples/pydantic/tutorial_3.py
examples/pydantic/tutorial_4.py
examples/quart/README.rst
examples/quart/__init__.py
examples/quart/main.py
examples/quart/models.py
examples/relations.py
examples/relations_recursive.py
examples/relations_with_unique.py
examples/router.py
examples/sanic/README.rst
examples/sanic/__init__.py
examples/sanic/_tests.py
examples/sanic/main.py
examples/sanic/models.py
examples/schema_create.py
examples/signals.py
examples/starlette/README.rst
examples/starlette/__init__.py
examples/starlette/main.py
examples/starlette/models.py
examples/transactions.py
examples/two_databases.py
tortoise/__init__.py
tortoise/backends/__init__.py
tortoise/backends/asyncpg/__init__.py
tortoise/backends/asyncpg/client.py
tortoise/backends/asyncpg/executor.py
tortoise/backends/asyncpg/schema_generator.py
tortoise/backends/base/__init__.py
tortoise/backends/base/client.py
tortoise/backends/base/config_generator.py
tortoise/backends/base/executor.py
tortoise_orm-0.25.2.dist-info/METADATA
tortoise_orm-0.25.2.dist-info/WHEEL
tortoise_orm-0.25.2.dist-info/entry_points.txt
tortoise_orm-0.25.2.dist-info/licenses/LICENSE.txt
tortoise_orm-0.25.2.dist-info/RECORD
