Metadata-Version: 2.1
Name: tortoise-orm
Version: 0.25.2
Summary: Easy async ORM for python, built with relations in mind
Keywords: sql,mysql,postgres,psql,sqlite,aiosqlite,asyncpg,relational,database,rdbms,orm,object mapper,async,asyncio,aio,psycopg
Author-Email: Andrey Bondar <andrey@bondar.ru>, Nickolas Grigoriadis <nagrigoriadis@gmail.com>, long2ice <long2ice@gmail.com>
License: Apache-2.0
Classifier: License :: OSI Approved :: Apache Software License
Classifier: Development Status :: 3 - Alpha
Classifier: Intended Audience :: Developers
Classifier: Programming Language :: Python :: 3
Classifier: Programming Language :: Python :: 3.9
Classifier: Programming Language :: Python :: 3.10
Classifier: Programming Language :: Python :: 3.11
Classifier: Programming Language :: Python :: 3.12
Classifier: Programming Language :: Python :: 3.13
Classifier: Programming Language :: Python :: 3.14
Classifier: Programming Language :: Python :: Implementation :: CPython
Classifier: Programming Language :: Python :: Implementation :: PyPy
Classifier: Programming Language :: PL/SQL
Classifier: Framework :: AsyncIO
Classifier: Topic :: Software Development :: Libraries :: Python Modules
Classifier: Topic :: Database
Classifier: Operating System :: POSIX
Classifier: Operating System :: MacOS :: MacOS X
Classifier: Operating System :: Microsoft :: Windows
Project-URL: documentation, https://tortoise.github.io
Project-URL: homepage, https://github.com/tortoise/tortoise-orm
Project-URL: repository, https://github.com/tortoise/tortoise-orm.git
Requires-Python: >=3.9
Requires-Dist: pypika-tortoise<1.0.0,>=0.6.3
Requires-Dist: iso8601<3.0.0,>=2.1.0; python_version < "4.0"
Requires-Dist: aiosqlite<1.0.0,>=0.16.0
Requires-Dist: pytz
Provides-Extra: accel
Requires-Dist: ciso8601; sys_platform != "win32" and implementation_name == "cpython" and extra == "accel"
Requires-Dist: uvloop; sys_platform != "win32" and implementation_name == "cpython" and extra == "accel"
Requires-Dist: orjson; extra == "accel"
Provides-Extra: asyncpg
Requires-Dist: asyncpg; extra == "asyncpg"
Provides-Extra: aiomysql
Requires-Dist: aiomysql; extra == "aiomysql"
Provides-Extra: asyncmy
Requires-Dist: asyncmy<1.0.0,>=0.2.8; python_version < "4.0" and extra == "asyncmy"
Provides-Extra: psycopg
Requires-Dist: psycopg[binary,pool]<4.0.0,>=3.0.12; extra == "psycopg"
Provides-Extra: asyncodbc
Requires-Dist: asyncodbc<1.0.0,>=0.1.1; python_version < "4.0" and extra == "asyncodbc"
